oneNeuron/__init__.py
oneNeuron/perceptron.py
utils/__init__.py
utils/all_utils.py
oneNeuron_pypi_dushyant_mishra-0.0.3.dist-info/LICENSE
oneNeuron_pypi_dushyant_mishra-0.0.3.dist-info/METADATA
oneNeuron_pypi_dushyant_mishra-0.0.3.dist-info/WHEEL
oneNeuron_pypi_dushyant_mishra-0.0.3.dist-info/top_level.txt
oneNeuron_pypi_dushyant_mishra-0.0.3.dist-info/RECORD
