Metadata-Version: 2.1
Name: oneNeuron-pypi-dushyant-mishra
Version: 0.0.3
Summary: This project is an implementation of a simple perceptron
Home-page: https://github.com/dushyant-mishra/oneNeuron_pypi
Author: dushyant-mishra
Author-email: dushyant.mishra@gmail.com
License: UNKNOWN
Project-URL: Bug Tracker, https://github.com/dushyant-mishra/oneNeuron_pypi/issues
Platform: UNKNOWN
Classifier: Programming Language :: Python :: 3
Classifier: License :: OSI Approved :: MIT License
Classifier: Operating System :: OS Independent
Requires-Python: >=3.7
License-File: LICENSE
Requires-Dist: matplotlib (==3.5.1)
Requires-Dist: numpy (==1.21.5)
Requires-Dist: pandas (==1.3.5)
Requires-Dist: joblib (==1.1.0)
Requires-Dist: tqdm
